flowmancer/__init__.py
flowmancer/_version.py
flowmancer/checkpointer/__init__.py
flowmancer/checkpointer/checkpointer.py
flowmancer/checkpointer/database.py
flowmancer/checkpointer/file.py
flowmancer/eventbus/__init__.py
flowmancer/eventbus/execution.py
flowmancer/eventbus/log.py
flowmancer/exceptions.py
flowmancer/executor.py
flowmancer/extensions/__init__.py
flowmancer/extensions/extension.py
flowmancer/extensions/notifications/__init__.py
flowmancer/extensions/notifications/email.py
flowmancer/extensions/notifications/notification.py
flowmancer/extensions/notifications/pushover.py
flowmancer/extensions/notifications/slack.py
flowmancer/extensions/progressbar.py
flowmancer/flowmancer.py
flowmancer/jobdefinition/__init__.py
flowmancer/jobdefinition/file.py
flowmancer/lifecycle.py
flowmancer/loggers/__init__.py
flowmancer/loggers/file.py
flowmancer/loggers/logger.py
flowmancer/py.typed
flowmancer/task.py
flowmancer-0.12.4.dist-info/LICENSE
flowmancer-0.12.4.dist-info/WHEEL
flowmancer-0.12.4.dist-info/METADATA
flowmancer-0.12.4.dist-info/RECORD
