Metadata-Version: 2.1
Name: flowmancer
Version: 0.12.4
Summary: The Python Thing-Doer
License: MIT
Author: Nathan Lee
Author-email: lee.nathan.sh@outlook.com
Requires-Python: >=3.8.1,<4.0.0
Classifier: License :: OSI Approved :: MIT License
Classifier: Programming Language :: Python :: 3
Classifier: Programming Language :: Python :: 3.9
Classifier: Programming Language :: Python :: 3.10
Classifier: Programming Language :: Python :: 3.11
Requires-Dist: PyYAML (>=6.0.1,<7.0.0)
Requires-Dist: pydantic (>=2.6.3,<3.0.0)
Requires-Dist: requests (>=2.31.0,<3.0.0)
Requires-Dist: rich (>=13.7.1,<14.0.0)
Requires-Dist: types-pyyaml (>=6.0.12.42,<7.0.0.0)
Requires-Dist: urllib3 (>=2.2.1,<3.0.0)
